{
  "article_html": "",
  "authors": [
    "Sean Ingle"
  ],
  "canonical_link": "",
  "keywords": [],
  "meta_keywords": [
    "Floyd Mayweather v Manny Pacquiao",
    "Floyd Mayweather",
    "Manny Pacquiao",
    "Boxing",
    "Sport",
    "US sports"
  ],
  "ntitle": "floyd_mayweather_may_believe_his_hype_but_history_will_never_agree",
  "publish_date": "2015-05-03T00:00:00",
  "tags": [],
  "text": "invalid_text",
  "title": "Floyd Mayweather may believe his hype but history will never agree",
  "ts_in": "2015-05-03T20:53:36.981964",
  "url": "http://www.theguardian.com/sport/blog/2015/may/03/floyd-mayweather-manny-pacquiao-sean-ingle"
}