{
  "article_html": "<div><p class=\"content__standfirst\">\n\nThe former Florida governor Jeb Bush says the Baltimore mom who smacked her son around at the riots this week reminded him of his own mother, former first lady Barbara Bush. During an interview with the National Review's editor, Rich Lowry, on Thursday at the NRI Ideas Summit in Washington, DC, Bush said the video of mother Toya Graham smacking her son Michael Singleton, for throwing rocks at police in Baltimore, was 'a nice visual symbol of what needs to be restored'.\n</p>\n</div>",
  "authors": [
    "Source Reuters"
  ],
  "canonical_link": "",
  "keywords": [],
  "meta_keywords": [
    "Jeb Bush",
    "Freddie Gray",
    "Baltimore",
    "US news",
    "World news",
    "Maryland",
    "Republicans",
    "US politics",
    "US elections 2016"
  ],
  "ntitle": "jeb_says_baltimore_mom_reminds_him_of_barbara_bush_video",
  "publish_date": "2015-05-01T00:00:00",
  "tags": [],
  "text": "The former Florida governor Jeb Bush says the Baltimore mom who smacked her son around at the riots this week reminded him of his own mother, former first lady Barbara Bush. During an interview with the National Review's editor, Rich Lowry, on Thursday at the NRI Ideas Summit in Washington, DC, Bush said the video of mother Toya Graham smacking her son Michael Singleton, for throwing rocks at police in Baltimore, was 'a nice visual symbol of what needs to be restored'.",
  "title": "Jeb says Baltimore mom reminds him of Barbara Bush - video",
  "ts_in": "2015-05-03T15:16:33.883151",
  "url": "http://www.theguardian.com/us-news/video/2015/may/01/jeb-baltimore-mom-reminds-him-barbara-bush-video"
}