{
  "article_html": "",
  "authors": [
    "Armando Iannucci"
  ],
  "canonical_link": "",
  "keywords": [],
  "meta_keywords": [
    "General election 2015",
    "Voter apathy",
    "Immigration and asylum",
    "Politics",
    "UK news"
  ],
  "ntitle": "our_better_selves_are_bold_and_inclusive",
  "publish_date": "2015-05-03T00:00:00",
  "tags": [],
  "text": "",
  "title": "Our better selves are bold and inclusive",
  "ts_in": "2015-05-03T15:16:59.523492",
  "url": "http://www.theguardian.com/commentisfree/2015/may/03/armando-iannucci-general-election-better-selves-bold-and-inclusive"
}